setup.py
osahon_distributions/Binomialdistribution.py
osahon_distributions/Gaussiandistribution.py
osahon_distributions/Generaldistribution.py
osahon_distributions/__init__.py
osahon_distributions.egg-info/PKG-INFO
osahon_distributions.egg-info/SOURCES.txt
osahon_distributions.egg-info/dependency_links.txt
osahon_distributions.egg-info/not-zip-safe
osahon_distributions.egg-info/top_level.txt